yandex_market_language/__init__.py
yandex_market_language/exceptions.py
yandex_market_language/yml.py
yandex_market_language/models/__init__.py
yandex_market_language/models/abstract.py
yandex_market_language/models/age.py
yandex_market_language/models/category.py
yandex_market_language/models/condition.py
yandex_market_language/models/currency.py
yandex_market_language/models/dimensions.py
yandex_market_language/models/feed.py
yandex_market_language/models/gift.py
yandex_market_language/models/offers.py
yandex_market_language/models/option.py
yandex_market_language/models/parameter.py
yandex_market_language/models/price.py
yandex_market_language/models/promo.py
yandex_market_language/models/shop.py
yandex_market_language/models/fields/__init__.py
yandex_market_language/models/fields/enable_auto_discounts.py
yandex_market_language/models/fields/options.py
yandex_market_language/models/fields/year.py
yandex_market_language-0.6.1.dist-info/AUTHORS.rst
yandex_market_language-0.6.1.dist-info/LICENSE
yandex_market_language-0.6.1.dist-info/METADATA
yandex_market_language-0.6.1.dist-info/WHEEL
yandex_market_language-0.6.1.dist-info/top_level.txt
yandex_market_language-0.6.1.dist-info/RECORD
