Metadata-Version: 2.1
Name: yandex-market-language
Version: 0.6.1
Summary: Yandex Market Language for Python provides user-friendly interface for parsing or creating XML files.
Home-page: https://github.com/stefanitsky/yandex_market_language
Author: Alexandr Stefanitsky-Mozdor
Author-email: stefanitsky.mozdor@gmail.com
License: GNU General Public License v3
Keywords: yandex_market_language
Platform: UNKNOWN
Classifier: Development Status :: 2 - Pre-Alpha
Classifier: Intended Audience :: Developers
Classifier: License :: OSI Approved :: GNU General Public License v3 (GPLv3)
Classifier: Natural Language :: English
Classifier: Programming Language :: Python :: 3
Classifier: Programming Language :: Python :: 3.5
Classifier: Programming Language :: Python :: 3.6
Classifier: Programming Language :: Python :: 3.7
Classifier: Programming Language :: Python :: 3.8
Requires-Python: >=3.5
